fossilci/__init__.py
fossilci/__main__.py
fossilci/commands.py
fossilci/env.py
fossilci/message_parser.py
fossilci/utils.py
fossilci/go/__init__.py
fossilci/go/build.py
fossilci/go/commands.py
fossilci/go/env.py
fossilci/go/prepare.py
fossilci/go/test.py
fossilci/go/utils.py
fossilci/node/__init__.py
fossilci/node/build.py
fossilci/node/test.py
fossilci/python/__init__.py
fossilci/python/build.py
fossilci/python/test.py
fossilci/ruby/__init__.py
fossilci/ruby/build.py
fossilci/ruby/test.py
fossilci/scala/__init__.py
fossilci/scala/build.py
fossilci/scala/test.py
fossilci-0.1.0.dist-info/DESCRIPTION.rst
fossilci-0.1.0.dist-info/METADATA
fossilci-0.1.0.dist-info/RECORD
fossilci-0.1.0.dist-info/WHEEL
fossilci-0.1.0.dist-info/entry_points.txt
fossilci-0.1.0.dist-info/metadata.json
fossilci-0.1.0.dist-info/top_level.txt
