Metadata-Version: 2.0
Name: fossilci
Version: 0.1.0
Summary: Fossil CI build tool
Home-page: UNKNOWN
Author: UNKNOWN
Author-email: UNKNOWN
License: UNKNOWN
Platform: UNKNOWN
